parserBioinfo/__init__.py
parserBioinfo/blast2csv.py
parserBioinfo/sqlite2excel.py
parserBioinfo-0.0.1.dist-info/LICENSE
parserBioinfo-0.0.1.dist-info/METADATA
parserBioinfo-0.0.1.dist-info/WHEEL
parserBioinfo-0.0.1.dist-info/top_level.txt
parserBioinfo-0.0.1.dist-info/RECORD
