Metadata-Version: 2.1
Name: parserBioinfo
Version: 0.0.1
Home-page: https://github.com/xianyu-123/sqllite2excel
Author: Guijiang
Author-email: guijiang_wang@163.com
License: Apache
Classifier: License :: OSI Approved :: Apache Software License
Classifier: Natural Language :: English
Classifier: Operating System :: OS Independent
Classifier: Programming Language :: Python
Classifier: Programming Language :: Python :: 3.6
Classifier: Topic :: Software Development :: Libraries :: Python Modules
Requires-Python: >=3.6
License-File: LICENSE
Requires-Dist: pandas >=1.2.5
Requires-Dist: openpyxl >=3.1.2
Requires-Dist: numpy
